mthasher/__init__.py
mthasher/__main__.py
mthasher/digest.py
mthasher/version.py
mthasher-2.0.4.dist-info/entry_points.txt
mthasher-2.0.4.dist-info/LICENSE
mthasher-2.0.4.dist-info/WHEEL
mthasher-2.0.4.dist-info/METADATA
mthasher-2.0.4.dist-info/RECORD
