Metadata-Version: 2.1
Name: mthasher
Version: 2.0.4
Summary: Calculate multiple hash digests for a piece of data in parallel, one algo/thread.
Home-page: https://github.com/ELTE-DH/mthasher
License: MIT
Author: dlazesz
Requires-Python: >=3.8,<4.0
Classifier: Development Status :: 5 - Production/Stable
Classifier: Intended Audience :: Developers
Classifier: License :: OSI Approved :: MIT License
Classifier: Operating System :: OS Independent
Classifier: Programming Language :: Python :: 3
Classifier: Programming Language :: Python :: 3.10
Classifier: Programming Language :: Python :: 3.8
Classifier: Programming Language :: Python :: 3.9
Classifier: Topic :: Software Development :: Libraries :: Python Modules
Project-URL: Repository, https://github.com/ELTE-DH/mthasher
